reversejp-0.1.1.dist-info/METADATA
reversejp-0.1.1.dist-info/WHEEL
reversejp.pyi
reversejp/__init__.py
reversejp/__init__.pyi
reversejp/py.typed
reversejp/reversejp.pyd
reversejp-0.1.1.dist-info/RECORD
