Metadata-Version: 2.4
Name: reversejp
Version: 0.1.1
Summary: Japan Geo Reverse Lookup
License: MIT
Requires-Python: >=3.9
Project-URL: Documentation, https://github.com/ringsaturn/reversejp
Project-URL: Source Code, https://github.com/ringsaturn/reversejp
